README.rst
setup.py
django_dev_commands/__init__.py
django_dev_commands/models.py
django_dev_commands.egg-info/PKG-INFO
django_dev_commands.egg-info/SOURCES.txt
django_dev_commands.egg-info/dependency_links.txt
django_dev_commands.egg-info/requires.txt
django_dev_commands.egg-info/top_level.txt
django_dev_commands/management/__init__.py
django_dev_commands/management/commands/__init__.py
django_dev_commands/management/commands/call.py
django_dev_commands/management/commands/commands.py
django_dev_commands/management/commands/conf.py
django_dev_commands/management/commands/run.py
django_dev_commands/management/commands/settings.py