Metadata-Version: 1.1
Name: django-dev-commands
Version: 1.1.1
Summary: Useful commands for developing Django applications.
Home-page: https://github.com/ikame/django-dev-commands
Author: ikame
Author-email: anler86@gmail.com
License: MIT
Keywords: django development dev tools utilities
Platform: UNKNOWN
Classifier: Environment :: Plugins
Classifier: Environment :: Console
Classifier: Environment :: Web Environment
Classifier: Intended Audience :: Developers
Classifier: Intended Audience :: Financial and Insurance Industry
Classifier: Framework :: Django
Classifier: Topic :: Database :: Front-Ends
Classifier: Topic :: Documentation
Classifier: Topic :: Internet :: WWW/HTTP :: Dynamic Content
Classifier: Topic :: Internet :: WWW/HTTP :: Site Management
Classifier: Topic :: Internet :: WWW/HTTP :: WSGI :: Application
Classifier: Programming Language :: Python :: 2.7
Classifier: Programming Language :: Python :: 3.3
Classifier: Topic :: Software Development :: Libraries :: Python Modules
